caikit/runtime/WatsonNlp/categoriestaskrequest_pb2.py
caikit/runtime/WatsonNlp/classificationtaskrequest_pb2.py
caikit/runtime/WatsonNlp/conceptstaskrequest_pb2.py
caikit/runtime/WatsonNlp/detagtaskrequest_pb2.py
caikit/runtime/WatsonNlp/emotiontaskrequest_pb2.py
caikit/runtime/WatsonNlp/entitymentionstaskrequest_pb2.py
caikit/runtime/WatsonNlp/keywordstaskrequest_pb2.py
caikit/runtime/WatsonNlp/langdetecttaskrequest_pb2.py
caikit/runtime/WatsonNlp/nounphrasestaskrequest_pb2.py
caikit/runtime/WatsonNlp/relationstaskrequest_pb2.py
caikit/runtime/WatsonNlp/rulestaskrequest_pb2.py
caikit/runtime/WatsonNlp/sentimenttaskrequest_pb2.py
caikit/runtime/WatsonNlp/syntaxtaskrequest_pb2.py
caikit/runtime/WatsonNlp/targetssentimenttaskrequest_pb2.py
caikit/runtime/WatsonNlp/topicstaskrequest_pb2.py
caikit_data_model/langcode_pb2.py
caikit_data_model/common/boolsequence_pb2.py
caikit_data_model/common/directory_pb2.py
caikit_data_model/common/file_pb2.py
caikit_data_model/common/filereference_pb2.py
caikit_data_model/common/floatsequence_pb2.py
caikit_data_model/common/intsequence_pb2.py
caikit_data_model/common/listoffilereferences_pb2.py
caikit_data_model/common/producerid_pb2.py
caikit_data_model/common/producerpriority_pb2.py
caikit_data_model/common/s3base_pb2.py
caikit_data_model/common/s3files_pb2.py
caikit_data_model/common/s3path_pb2.py
caikit_data_model/common/strsequence_pb2.py
caikit_data_model/common/trainingstatus_pb2.py
caikit_data_model/common/runtime/runtimeinforequest_pb2.py
caikit_data_model/common/runtime/runtimeinforesponse_pb2.py
caikit_data_model/runtime/modelpointer_pb2.py
caikit_data_model/runtime/traininginforequest_pb2.py
caikit_data_model/runtime/trainingjob_pb2.py
caikit_data_model/runtime/trainingstatusresponse_pb2.py
watson_nlp_data_model/aggregatedemotionprediction_pb2.py
watson_nlp_data_model/aggregatedsentiment_pb2.py
watson_nlp_data_model/aggregatesentimentprediction_pb2.py
watson_nlp_data_model/atomicsentiment_pb2.py
watson_nlp_runtime_client-2.0.1.dist-info/METADATA
watson_nlp_runtime_client-2.0.1.dist-info/WHEEL
watson_nlp_runtime_client-2.0.1.dist-info/top_level.txt
watson_nlp_runtime_client-2.0.1.dist-info/RECORD
